{
	"credit": "Made with Blockbench",
	"texture_size": [32, 32],
	"textures": {
		"4": "block/brown_wool",
		"5": "block/gold_block",
		"6": "block/dark_oak_log",
		"7": "block/pasted",
		"particle": "block/hay_block_side"
	},
	"elements": [
		{
			"from": [6.4, 3.2, 1],
			"to": [12.9, 4.2, 2],
			"rotation": {"angle": 0, "axis": "y", "origin": [5.6, 3.2, 0]},
			"faces": {
				"north": {"uv": [0, 6.42857, 1.67143, 11.18571], "texture": "#6"},
				"east": {"uv": [1.28571, 7.71429, 1.54286, 12.21429], "texture": "#6"},
				"south": {"uv": [2.57143, 0, 2.57143, 7.07143], "texture": "#6"},
				"west": {"uv": [1.54286, 7.71429, 1.8, 12.34286], "texture": "#6"},
				"up": {"uv": [4.24286, 1.92857, 2.57143, 0.64286], "texture": "#6"},
				"down": {"uv": [4.24286, 1.28571, 2.57143, 5.27143], "texture": "#6"}
			}
		},
		{
			"from": [12.8, 3.9, 1],
			"to": [19.2, 4.9, 2],
			"rotation": {"angle": 0, "axis": "y", "origin": [11.9, 3.9, 0]},
			"faces": {
				"north": {"uv": [2.46857, 1.92857, 4.24286, 6.68571], "texture": "#6"},
				"east": {"uv": [1.28571, 8.35714, 1.54286, 12.85714], "texture": "#6"},
				"south": {"uv": [1.8, 6.42857, 1.8, 13.5], "texture": "#6"},
				"west": {"uv": [1.54286, 8.35714, 1.8, 12.98571], "texture": "#6"},
				"up": {"uv": [1.67143, 8.22857, 0, 7.07143], "texture": "#6"},
				"down": {"uv": [4.5, 2.57143, 2.82857, 6.55714], "texture": "#6"}
			}
		},
		{
			"from": [17, 4, 0.95],
			"to": [19.05, 4.8, 1.05],
			"rotation": {"angle": 0, "axis": "y", "origin": [11.9, 3.9, 0]},
			"faces": {
				"north": {"uv": [0, 4.05357, 16, 12.17738], "texture": "#7"},
				"east": {"uv": [1.28571, 14.26548, 2.81786, 12.85714], "texture": "#7"},
				"south": {"uv": [0, 3.9869, 16, 12.125], "texture": "#7"},
				"west": {"uv": [1.54286, 14.26548, 3.075, 12.98571], "texture": "#7"},
				"up": {"uv": [6.40476, 14.32857, 4.73333, 13.17143], "texture": "#7"},
				"down": {"uv": [3.54167, 2.57143, 2.82857, 3.37381], "texture": "#7"}
			}
		},
		{
			"from": [17, 4, 1.95],
			"to": [19.05, 4.8, 2.05],
			"rotation": {"angle": 0, "axis": "y", "origin": [11.9, 3.9, 0]},
			"faces": {
				"north": {"uv": [0, 4.05357, 16, 12.17738], "texture": "#7"},
				"east": {"uv": [1.28571, 14.26548, 2.81786, 12.85714], "texture": "#7"},
				"south": {"uv": [0, 3.9869, 16, 12.125], "texture": "#7"},
				"west": {"uv": [1.54286, 14.26548, 3.075, 12.98571], "texture": "#7"},
				"up": {"uv": [6.40476, 14.32857, 4.73333, 13.17143], "texture": "#7"},
				"down": {"uv": [3.54167, 2.57143, 2.82857, 3.37381], "texture": "#7"}
			}
		},
		{
			"from": [-0.7, 2.6, -0.5],
			"to": [1.5, 5.3, 3.5],
			"rotation": {"angle": 0, "axis": "y", "origin": [0, 3.6, -0.5]},
			"faces": {
				"north": {"uv": [14.01971, 5.68512, 6.88359, 4.34886], "rotation": 90, "texture": "#4"},
				"east": {"uv": [11.55641, 5.63685, 5.42635, 4.3431], "rotation": 90, "texture": "#4"},
				"south": {"uv": [15.6, 4.34938, 2.96306, 6.66728], "rotation": 90, "texture": "#4"},
				"west": {"uv": [5.9188, 8.80288, 8.30831, 4.34467], "rotation": 90, "texture": "#4"},
				"up": {"uv": [5.42635, 4.34703, 12.37751, 5.08717], "rotation": 90, "texture": "#4"},
				"down": {"uv": [6.24745, 5.5518, 13.19861, 4.34389], "rotation": 90, "texture": "#4"}
			}
		},
		{
			"from": [-1.5, 3.2, 0.4],
			"to": [-0.6, 4.7, 2.6],
			"rotation": {"angle": 0, "axis": "y", "origin": [0, 3.6, -0.5]},
			"faces": {
				"north": {"uv": [14.01971, 5.68512, 6.88359, 4.34886], "rotation": 90, "texture": "#4"},
				"east": {"uv": [11.55641, 5.63685, 5.42635, 4.3431], "rotation": 90, "texture": "#4"},
				"south": {"uv": [15.6, 4.34938, 2.96306, 6.66728], "rotation": 90, "texture": "#4"},
				"west": {"uv": [5.9188, 8.80288, 8.30831, 4.34467], "rotation": 90, "texture": "#4"},
				"up": {"uv": [5.42635, 4.34703, 12.37751, 5.08717], "rotation": 90, "texture": "#4"},
				"down": {"uv": [6.24745, 5.5518, 13.19861, 4.34389], "rotation": 90, "texture": "#4"}
			}
		},
		{
			"from": [-2, 3.4, 0.9],
			"to": [-1.1, 4.3, 2.3],
			"rotation": {"angle": 0, "axis": "y", "origin": [0, 3.6, -0.5]},
			"faces": {
				"north": {"uv": [14.01971, 5.68512, 6.88359, 4.34886], "rotation": 90, "texture": "#4"},
				"east": {"uv": [11.55641, 5.63685, 5.42635, 4.3431], "rotation": 90, "texture": "#4"},
				"south": {"uv": [15.6, 4.34938, 2.96306, 6.66728], "rotation": 90, "texture": "#4"},
				"west": {"uv": [5.9188, 8.80288, 8.30831, 4.34467], "rotation": 90, "texture": "#4"},
				"up": {"uv": [5.42635, 4.34703, 12.37751, 5.08717], "rotation": 90, "texture": "#4"},
				"down": {"uv": [6.24745, 5.5518, 13.19861, 4.34389], "rotation": 90, "texture": "#4"}
			}
		},
		{
			"from": [1.4, 2.2, -0.3],
			"to": [4, 5, 3.4],
			"rotation": {"angle": 0, "axis": "y", "origin": [3, 3.2, -0.6]},
			"faces": {
				"north": {"uv": [13.19861, 5.68146, 6.26776, 4.34546], "rotation": 90, "texture": "#4"},
				"east": {"uv": [9.91422, 5.63685, 3.57888, 4.34336], "rotation": 90, "texture": "#4"},
				"south": {"uv": [15.63723, 4.34703, 6.45273, 6.1203], "rotation": 90, "texture": "#4"},
				"west": {"uv": [9.91422, 5.65968, 3.57888, 4.34493], "rotation": 90, "texture": "#4"},
				"up": {"uv": [3.16834, 4.34676, 9.91422, 5.08717], "rotation": 90, "texture": "#4"},
				"down": {"uv": [4.39998, 5.55493, 11.14587, 4.34676], "rotation": 90, "texture": "#4"}
			}
		},
		{
			"from": [4, 2.5, 0.3],
			"to": [5, 4.7, 2.7],
			"rotation": {"angle": 0, "axis": "y", "origin": [5.8, 2.9, -0.1]},
			"faces": {
				"north": {"uv": [0.73481, 6.08192, 10.1306, 4.34479], "rotation": 90, "texture": "#4"},
				"east": {"uv": [0, 5.64296, 4.70945, 4.34836], "rotation": 90, "texture": "#4"},
				"south": {"uv": [12.47119, 6.08591, 1.54435, 4.34747], "rotation": 90, "texture": "#4"},
				"west": {"uv": [4.74435, 5.66511, 10.95517, 4.34925], "rotation": 90, "texture": "#4"},
				"up": {"uv": [5.16073, 5.08613, 11.89203, 4.34543], "rotation": 90, "texture": "#4"},
				"down": {"uv": [7.83231, 5.55702, 1.62149, 4.34791], "rotation": 90, "texture": "#4"}
			}
		},
		{
			"from": [5, 2.5, 0.3],
			"to": [5.2, 4.7, 2.7],
			"rotation": {"angle": 0, "axis": "y", "origin": [5.8, 2.9, -0.1]},
			"faces": {
				"north": {"uv": [9.4968, 4.64815, 12.362, 10.66296], "texture": "#5"},
				"east": {"uv": [1, 7.51235, 3.47, 13.24074], "texture": "#5"},
				"south": {"uv": [10.88, 6.7963, 13.35, 8.2284], "texture": "#5"},
				"west": {"uv": [10.88, 8.2284, 13.35, 14.1], "texture": "#5"},
				"up": {"uv": [12.362, 4.86296, 9.892, 2.5], "texture": "#5"},
				"down": {"uv": [8.41, 6.7963, 5.94, 12.30988], "texture": "#5"}
			}
		},
		{
			"from": [5.2, 2.5, 0.3],
			"to": [5.7, 4.7, 2.7],
			"rotation": {"angle": 0, "axis": "y", "origin": [5.8, 2.9, -0.1]},
			"faces": {
				"north": {"uv": [7.40855, 5.68139, 14.35622, 4.34432], "rotation": 90, "texture": "#4"},
				"east": {"uv": [3.95915, 5.63987, 10.72186, 4.34532], "rotation": 90, "texture": "#4"},
				"south": {"uv": [13.51928, 5.69951, 7.99733, 4.34507], "rotation": 90, "texture": "#4"},
				"west": {"uv": [7.99733, 5.66138, 14.76004, 4.34558], "rotation": 90, "texture": "#4"},
				"up": {"uv": [14.35622, 4.34369, 7.59351, 5.08529], "rotation": 90, "texture": "#4"},
				"down": {"uv": [12.74095, 5.55457, 5.97824, 4.3452], "rotation": 90, "texture": "#4"}
			}
		},
		{
			"from": [5.7, 2.5, 0.3],
			"to": [5.9, 4.7, 2.7],
			"rotation": {"angle": 0, "axis": "y", "origin": [5.8, 2.9, -0.1]},
			"faces": {
				"north": {"uv": [9.4968, 4.64815, 12.362, 10.66296], "texture": "#5"},
				"east": {"uv": [1, 7.51235, 3.47, 13.24074], "texture": "#5"},
				"south": {"uv": [10.88, 6.7963, 13.35, 8.2284], "texture": "#5"},
				"west": {"uv": [10.88, 8.2284, 13.35, 14.1], "texture": "#5"},
				"up": {"uv": [12.362, 4.86296, 9.892, 2.5], "texture": "#5"},
				"down": {"uv": [8.41, 6.7963, 5.94, 12.30988], "texture": "#5"}
			}
		},
		{
			"from": [4.711, 2.103, 1.3765],
			"to": [4.997, 3.104, 1.6625],
			"rotation": {"angle": 0, "axis": "y", "origin": [4.854, 4.147, -3.583]},
			"faces": {
				"north": {"uv": [9.4968, 4.64815, 12.362, 10.66296], "texture": "#5"},
				"east": {"uv": [1, 7.51235, 3.47, 13.24074], "texture": "#5"},
				"south": {"uv": [10.88, 6.7963, 13.35, 8.2284], "texture": "#5"},
				"west": {"uv": [10.88, 8.2284, 13.35, 14.1], "texture": "#5"},
				"up": {"uv": [12.362, 4.86296, 9.892, 2.5], "texture": "#5"},
				"down": {"uv": [8.41, 6.7963, 5.94, 12.30988], "texture": "#5"}
			}
		},
		{
			"from": [4.711, 1.102, 1.0905],
			"to": [4.997, 2.103, 1.3765],
			"rotation": {"angle": 0, "axis": "y", "origin": [4.854, 4.147, -3.583]},
			"faces": {
				"north": {"uv": [9.4968, 4.64815, 12.362, 10.66296], "texture": "#5"},
				"east": {"uv": [1, 7.51235, 3.47, 13.24074], "texture": "#5"},
				"south": {"uv": [10.88, 6.7963, 13.35, 8.2284], "texture": "#5"},
				"west": {"uv": [10.88, 8.2284, 13.35, 14.1], "texture": "#5"},
				"up": {"uv": [12.362, 4.86296, 9.892, 2.5], "texture": "#5"},
				"down": {"uv": [8.41, 6.7963, 5.94, 12.30988], "texture": "#5"}
			}
		},
		{
			"from": [4.711, 0.959, -0.4825],
			"to": [4.997, 1.245, 1.2335],
			"rotation": {"angle": 0, "axis": "y", "origin": [4.854, 4.147, -3.583]},
			"faces": {
				"north": {"uv": [9.4968, 4.64815, 12.362, 10.66296], "texture": "#5"},
				"east": {"uv": [1, 7.51235, 3.47, 13.24074], "texture": "#5"},
				"south": {"uv": [10.88, 6.7963, 13.35, 8.2284], "texture": "#5"},
				"west": {"uv": [10.88, 8.2284, 13.35, 14.1], "texture": "#5"},
				"up": {"uv": [12.362, 4.86296, 9.892, 2.5], "texture": "#5"},
				"down": {"uv": [8.41, 6.7963, 5.94, 12.30988], "texture": "#5"}
			}
		},
		{
			"from": [4.711, 1.102, -0.7685],
			"to": [4.997, 1.674, -0.4825],
			"rotation": {"angle": 0, "axis": "y", "origin": [4.854, 4.147, -3.583]},
			"faces": {
				"north": {"uv": [9.4968, 4.64815, 12.362, 10.66296], "texture": "#5"},
				"east": {"uv": [1, 7.51235, 3.47, 13.24074], "texture": "#5"},
				"south": {"uv": [10.88, 6.7963, 13.35, 8.2284], "texture": "#5"},
				"west": {"uv": [10.88, 8.2284, 13.35, 14.1], "texture": "#5"},
				"up": {"uv": [12.362, 4.86296, 9.892, 2.5], "texture": "#5"},
				"down": {"uv": [8.41, 6.7963, 5.94, 12.30988], "texture": "#5"}
			}
		},
		{
			"from": [4.711, 1.102, 1.6625],
			"to": [4.997, 2.103, 1.9485],
			"rotation": {"angle": 0, "axis": "y", "origin": [4.854, 4.147, 19.583]},
			"faces": {
				"north": {"uv": [13.35, 6.7963, 10.88, 8.2284], "texture": "#5"},
				"east": {"uv": [3.47, 7.51235, 1, 13.24074], "texture": "#5"},
				"south": {"uv": [12.362, 4.64815, 9.4968, 10.66296], "texture": "#5"},
				"west": {"uv": [13.35, 8.2284, 10.88, 14.1], "texture": "#5"},
				"up": {"uv": [12.362, 2.5, 9.892, 4.86296], "texture": "#5"},
				"down": {"uv": [8.41, 12.30988, 5.94, 6.7963], "texture": "#5"}
			}
		},
		{
			"from": [4.711, 0.959, 1.8055],
			"to": [4.997, 1.245, 3.6645],
			"rotation": {"angle": 0, "axis": "y", "origin": [4.854, 4.147, 19.583]},
			"faces": {
				"north": {"uv": [13.35, 6.7963, 10.88, 8.2284], "texture": "#5"},
				"east": {"uv": [3.47, 7.51235, 1, 13.24074], "texture": "#5"},
				"south": {"uv": [12.362, 4.64815, 9.4968, 10.66296], "texture": "#5"},
				"west": {"uv": [13.35, 8.2284, 10.88, 14.1], "texture": "#5"},
				"up": {"uv": [12.362, 2.5, 9.892, 4.86296], "texture": "#5"},
				"down": {"uv": [8.41, 12.30988, 5.94, 6.7963], "texture": "#5"}
			}
		},
		{
			"from": [4.711, 1.102, 3.5215],
			"to": [4.997, 1.674, 3.8075],
			"rotation": {"angle": 0, "axis": "y", "origin": [4.854, 4.147, 19.583]},
			"faces": {
				"north": {"uv": [13.35, 6.7963, 10.88, 8.2284], "texture": "#5"},
				"east": {"uv": [3.47, 7.51235, 1, 13.24074], "texture": "#5"},
				"south": {"uv": [12.362, 4.64815, 9.4968, 10.66296], "texture": "#5"},
				"west": {"uv": [13.35, 8.2284, 10.88, 14.1], "texture": "#5"},
				"up": {"uv": [12.362, 2.5, 9.892, 4.86296], "texture": "#5"},
				"down": {"uv": [8.41, 12.30988, 5.94, 6.7963], "texture": "#5"}
			}
		},
		{
			"from": [5.9, 2.5, 0.3],
			"to": [6.6, 4.7, 2.7],
			"rotation": {"angle": 0, "axis": "y", "origin": [5.8, 2.9, -0.1]},
			"faces": {
				"north": {"uv": [7.40855, 5.68139, 14.35622, 4.34432], "rotation": 90, "texture": "#4"},
				"east": {"uv": [3.95915, 5.63987, 10.72186, 4.34532], "rotation": 90, "texture": "#4"},
				"south": {"uv": [11.57718, 5.67825, 7.99733, 4.34507], "rotation": 90, "texture": "#4"},
				"west": {"uv": [7.99733, 5.66138, 14.76004, 4.34558], "rotation": 90, "texture": "#4"},
				"up": {"uv": [14.35622, 4.34369, 7.59351, 5.08529], "rotation": 90, "texture": "#4"},
				"down": {"uv": [12.74095, 5.55457, 5.97824, 4.3452], "rotation": 90, "texture": "#4"}
			}
		}
	],
	"display": {
		"thirdperson_righthand": {
			"rotation": [19, 78, 86],
			"translation": [9, -5.75, 8.75],
			"scale": [1.61, 1.61, 1.61]
		},
		"thirdperson_lefthand": {
			"rotation": [7, -105, -85],
			"translation": [-12.25, -5.75, 5],
			"scale": [1.61, 1.61, 1.61]
		},
		"firstperson_righthand": {
			"rotation": [0, 94, 0],
			"translation": [-1, 4.25, 0]
		},
		"firstperson_lefthand": {
			"rotation": [0, -84, 0],
			"translation": [-13.5, 4, 1.25]
		},
		"ground": {
			"translation": [0, 3, 4.75]
		},
		"gui": {
			"rotation": [-33, 0, 58],
			"translation": [-3, 4.25, 0],
			"scale": [0.9, 0.9, 0.9]
		},
		"head": {
			"translation": [0, 12, 7.75]
		},
		"fixed": {
			"translation": [0, 2.75, 3.75]
		}
	}
}