{
    "parent": "minecraft:item/generated",
        "textures": {
          "layer0": "minecraft:item/diamond_axe"
        },
	
	"overrides":[
	
	{"predicate": {"custom_model_data":1}, "model": "custom/popcart"},
	{"predicate": {"custom_model_data":2}, "model": "custom/plain_mickey_ears"},
	{"predicate": {"custom_model_data":3}, "model": "custom/mmplush"},
	{"predicate": {"custom_model_data":4}, "model": "custom/maintr"},
	{"predicate": {"custom_model_data":5}, "model": "custom/cathat"},
	{"predicate": {"custom_model_data":6}, "model": "custom/minion"},
	{"predicate": {"custom_model_data":7}, "model": "custom/gsarc"},
	{"predicate": {"custom_model_data":8}, "model": "custom/shrek"},
	{"predicate": {"custom_model_data":9}, "model": "custom/miminion"},
	{"predicate": {"custom_model_data":10}, "model": "custom/express"},
	{"predicate": {"custom_model_data":11}, "model": "custom/golden_sarc"},
	{"predicate": {"custom_model_data":12}, "model": "custom/trex"},
	{"predicate": {"custom_model_data":13}, "model": "custom/click"},
	{"predicate": {"custom_model_data":14}, "model": "custom/logo"},
	{"predicate": {"custom_model_data":15}, "model": "custom/hatun"},
	{"predicate": {"custom_model_data":16}, "model": "custom/minioon"},
	{"predicate": {"custom_model_data":17}, "model": "custom/fast"},
	{"predicate": {"custom_model_data":18}, "model": "custom/auto"},
	{"predicate": {"custom_model_data":19}, "model": "custom/phone"},
	{"predicate": {"custom_model_data":20}, "model": "custom/moomy"},
	{"predicate": {"custom_model_data":21}, "model": "custom/homer"},
	{"predicate": {"custom_model_data":22}, "model": "custom/hpstat"},
	{"predicate": {"custom_model_data":23}, "model": "custom/rrr"},
	{"predicate": {"custom_model_data":24}, "model": "custom/monscafe"},
	{"predicate": {"custom_model_data":25}, "model": "custom/brazier"},
	{"predicate": {"custom_model_data":26}, "model": "custom/leximinion"},
	{"predicate": {"custom_model_data":27}, "model": "custom/onehun"},
	{"predicate": {"custom_model_data":28}, "model": "custom/shmic"},
	{"predicate": {"custom_model_data":29}, "model": "custom/astrodlr"},
	{"predicate": {"custom_model_data":30}, "model": "custom/bunny"},
	{"predicate": {"custom_model_data":31}, "model": "custom/micears"},
	{"predicate": {"custom_model_data":32}, "model": "custom/minbow"},
	{"predicate": {"custom_model_data":33}, "model": "custom/caseyp"},
	{"predicate": {"custom_model_data":34}, "model": "custom/rightarm"},
	{"predicate": {"custom_model_data":35}, "model": "custom/pinkheadb"},
	{"predicate": {"custom_model_data":36}, "model": "custom/swheadb"},
	{"predicate": {"custom_model_data":37}, "model": "custom/blueluma"},
	{"predicate": {"custom_model_data":38}, "model": "custom/applebag"},
	{"predicate": {"custom_model_data":39}, "model": "custom/tangled_sachel"},
	{"predicate": {"custom_model_data":40}, "model": "custom/tink"},
	{"predicate": {"custom_model_data":41}, "model": "custom/mario_hat"},
	{"predicate": {"custom_model_data":42}, "model": "custom/minmheadb"},
	{"predicate": {"custom_model_data":43}, "model": "custom/tinkears"},
	{"predicate": {"custom_model_data":44}, "model": "custom/bubblewand"},
	{"predicate": {"custom_model_data":45}, "model": "custom/tikiears"},
	{"predicate": {"custom_model_data":46}, "model": "custom/leftarm"},
	{"predicate": {"custom_model_data":47}, "model": "custom/peterpan"},
	{"predicate": {"custom_model_data":48}, "model": "custom/phoexp"},
	{"predicate": {"custom_model_data":49}, "model": "custom/phofod"},
	{"predicate": {"custom_model_data":50}, "model": "custom/phoauto"},
	{"predicate": {"custom_model_data":51}, "model": "custom/phoride"},
	{"predicate": {"custom_model_data":52}, "model": "custom/phopark"},
	{"predicate": {"custom_model_data":53}, "model": "custom/phosett"},
	{"predicate": {"custom_model_data":54}, "model": "custom/phoshop"},
	{"predicate": {"custom_model_data":55}, "model": "custom/phosho"},
	{"predicate": {"custom_model_data":56}, "model": "custom/phowar"},
	{"predicate": {"custom_model_data":57}, "model": "custom/hp"},
	{"predicate": {"custom_model_data":58}, "model": "custom/oswaldplushie"},
	{"predicate": {"custom_model_data":59}, "model": "custom/floundersp"},
	{"predicate": {"custom_model_data":60}, "model": "custom/arielheadband"},
	{"predicate": {"custom_model_data":61}, "model": "custom/dumbo"},
	{"predicate": {"custom_model_data":62}, "model": "custom/rupheadband"},
	{"predicate": {"custom_model_data":63}, "model": "custom/bed"},
	{"predicate": {"custom_model_data":64}, "model": "custom/mickeyplush"},
	{"predicate": {"custom_model_data":65}, "model": "custom/minnieplush"},
	{"predicate": {"custom_model_data":66}, "model": "custom/dumboride"},
	{"predicate": {"custom_model_data":67}, "model": "custom/teacup"},
	{"predicate": {"custom_model_data":68}, "model": "custom/lamp"},
	{"predicate": {"custom_model_data":69}, "model": "custom/peterpanride"},
	{"predicate": {"custom_model_data":70}, "model": "custom/bigb"},
	{"predicate": {"custom_model_data":71}, "model": "custom/fanlam"},
	{"predicate": {"custom_model_data":72}, "model": "custom/sail"},
	{"predicate": {"custom_model_data":73}, "model": "custom/rainbow"},
	{"predicate": {"custom_model_data":74}, "model": "custom/tictok"},
	{"predicate": {"custom_model_data":75}, "model": "custom/pixie-hollow-log"},
	{"predicate": {"custom_model_data":76}, "model": "custom/lightsaberone"},
	{"predicate": {"custom_model_data":77}, "model": "custom/jediplush"},
	{"predicate": {"custom_model_data":78}, "model": "custom/mickeyhun"},
	{"predicate": {"custom_model_data":79}, "model": "custom/arielplush"},
	{"predicate": {"custom_model_data":80}, "model": "custom/rapplush"},
	{"predicate": {"custom_model_data":81}, "model": "custom/unicornfloat"},
	{"predicate": {"custom_model_data":82}, "model": "custom/snowplush"},
	{"predicate": {"custom_model_data":83}, "model": "custom/leiaminnie"},
	{"predicate": {"custom_model_data":84}, "model": "custom/sabertwo"},
	{"predicate": {"custom_model_data":85}, "model": "custom/horns"},
	{"predicate": {"custom_model_data":86}, "model": "custom/madhatter"},
	{"predicate": {"custom_model_data":87}, "model": "custom/darthvader"},
	{"predicate": {"custom_model_data":88}, "model": "custom/yoda"},
	{"predicate": {"custom_model_data":89}, "model": "custom/flag"},
	{"predicate": {"custom_model_data":90}, "model": "custom/mmayhem"},
	{"predicate": {"custom_model_data":91}, "model": "custom/rrrocket"},
	{"predicate": {"custom_model_data":92}, "model": "custom/silly"},
	{"predicate": {"custom_model_data":93}, "model": "custom/uso"},
	{"predicate": {"custom_model_data":94}, "model": "custom/usoauto"},
	{"predicate": {"custom_model_data":95}, "model": "custom/dauto"},
	{"predicate": {"custom_model_data":96}, "model": "custom/disneyland"},
	{"predicate": {"custom_model_data":97}, "model": "custom/universal"},
	{"predicate": {"custom_model_data":98}, "model": "custom/hollywood"},
	{"predicate": {"custom_model_data":99}, "model": "custom/monster"},
	{"predicate": {"custom_model_data":100}, "model": "custom/emporium"},
	{"predicate": {"custom_model_data":101}, "model": "custom/dolewhip"},
	{"predicate": {"custom_model_data":102}, "model": "custom/carousel"},
	{"predicate": {"custom_model_data":103}, "model": "custom/castle"},
	{"predicate": {"custom_model_data":104}, "model": "custom/orbiter"},
	{"predicate": {"custom_model_data":105}, "model": "custom/hollyauto"},
	{"predicate": {"custom_model_data":106}, "model": "custom/dumbob"},
	{"predicate": {"custom_model_data":107}, "model": "custom/peterp"},
	{"predicate": {"custom_model_data":108}, "model": "custom/pinocchio"},
	{"predicate": {"custom_model_data":109}, "model": "custom/jollyb"},
	{"predicate": {"custom_model_data":110}, "model": "custom/linkyb"},
	{"predicate": {"custom_model_data":111}, "model": "custom/railroad"},
	{"predicate": {"custom_model_data":112}, "model": "custom/starbuckb"},
	{"predicate": {"custom_model_data":113}, "model": "custom/snowwb"},
	{"predicate": {"custom_model_data":114}, "model": "custom/tikiroom"},
	{"predicate": {"custom_model_data":115}, "model": "custom/tomorrowland"},
	{"predicate": {"custom_model_data":116}, "model": "custom/teacupb"},
	{"predicate": {"custom_model_data":117}, "model": "custom/ewokears"},
	{"predicate": {"custom_model_data":118}, "model": "custom/purpleear"},
	{"predicate": {"custom_model_data":119}, "model": "custom/ppears"},
	{"predicate": {"custom_model_data":120}, "model": "custom/prideh"},
	{"predicate": {"custom_model_data":121}, "model": "custom/pridee"},
	{"predicate": {"custom_model_data":122}, "model": "custom/rosegold"},
	{"predicate": {"custom_model_data":123}, "model": "custom/balloon"},
	{"predicate": {"custom_model_data":124}, "model": "custom/huncastlelamp"},
	{"predicate": {"custom_model_data":125}, "model": "custom/hunfairybanner"},
	{"predicate": {"custom_model_data":126}, "model": "custom/topflag"},
	{"predicate": {"custom_model_data":127}, "model": "custom/mshunban"},
	{"predicate": {"custom_model_data":128}, "model": "custom/balloons"},
	{"predicate": {"custom_model_data":129}, "model": "custom/ppfsign"},
	{"predicate": {"custom_model_data":130}, "model": "custom/fantrash"},
	{"predicate": {"custom_model_data":131}, "model": "custom/firetruck"},
	{"predicate": {"custom_model_data":132}, "model": "custom/paradetest"},
	{"predicate": {"custom_model_data":133}, "model": "custom/msbench"},
	{"predicate": {"custom_model_data":134}, "model": "custom/snowbook"},
	{"predicate": {"custom_model_data":135}, "model": "custom/baymax"},
	{"predicate": {"custom_model_data":136}, "model": "custom/bluefairy"},
	{"predicate": {"custom_model_data":137}, "model": "custom/snowcasket"},
	{"predicate": {"custom_model_data":138}, "model": "custom/snowdress"},
	{"predicate": {"custom_model_data":139}, "model": "custom/sword"},
	{"predicate": {"custom_model_data":140}, "model": "custom/large_vase"},
	{"predicate": {"custom_model_data":141}, "model": "custom/small_pot_1"},
	{"predicate": {"custom_model_data":142}, "model": "custom/mumarm"},
	{"predicate": {"custom_model_data":143}, "model": "custom/mumarmtwo"},
	{"predicate": {"custom_model_data":144}, "model": "custom/kneelinganubis"},
	{"predicate": {"custom_model_data":145}, "model": "custom/blue"},
	{"predicate": {"custom_model_data":146}, "model": "custom/surfpridef"},
	{"predicate": {"custom_model_data":147}, "model": "custom/cowsquish"},
	{"predicate": {"custom_model_data":148}, "model": "custom/mumrawr"},
	{"predicate": {"custom_model_data":149}, "model": "custom/broom"},
	{"predicate": {"custom_model_data":150}, "model": "custom/construction"},
	{"predicate": {"custom_model_data":151}, "model": "custom/lincarm"},
	{"predicate": {"custom_model_data":152}, "model": "custom/lincarmone"},
	{"predicate": {"custom_model_data":153}, "model": "custom/castmemberj"},
	{"predicate": {"custom_model_data":154}, "model": "custom/dinohat"},
	{"predicate": {"custom_model_data":155}, "model": "custom/sharkhat"},
	{"predicate": {"custom_model_data":156}, "model": "custom/dumboears"},
	{"predicate": {"custom_model_data":157}, "model": "custom/pinocchioears"},
	{"predicate": {"custom_model_data":158}, "model": "custom/totmickey"},
	{"predicate": {"custom_model_data":159}, "model": "custom/tothat"},
	{"predicate": {"custom_model_data":160}, "model": "custom/tothead"},
	{"predicate": {"custom_model_data":161}, "model": "custom/lucky-block"},
	{"predicate": {"custom_model_data":162}, "model": "custom/sdminecart"},
	{"predicate": {"custom_model_data":164}, "model": "custom/buzzwings"},
	{"predicate": {"custom_model_data":165}, "model": "custom/grogu"},
	{"predicate": {"custom_model_data":166}, "model": "custom/prideg"},
	{"predicate": {"custom_model_data":167}, "model": "custom/pridebp"},
	{"predicate": {"custom_model_data":168}, "model": "custom/astrogun"},
	{"predicate": {"custom_model_data":169}, "model": "custom/prideflag"},
	{"predicate": {"custom_model_data":170}, "model": "custom/astro_blaster"},
	{"predicate": {"custom_model_data":171}, "model": "custom/buzz_lightyear_wings"},
	{"predicate": {"custom_model_data":172}, "model": "custom/astromk"},
	{"predicate": {"custom_model_data":173}, "model": "custom/cart_buzz_lightyear_astro_blasters"},
	{"predicate": {"custom_model_data":174}, "model": "custom/horsie"},
	{"predicate": {"custom_model_data":175}, "model": "custom/turkeyleg"},
	{"predicate": {"custom_model_data":176}, "model": "custom/matterhorn_yeti"},
	{"predicate": {"custom_model_data":177}, "model": "custom/xwing"},
	{"predicate": {"custom_model_data":178}, "model": "custom/tie_fighter"},
	{"predicate": {"custom_model_data":179}, "model": "custom/buzzeh"},
	{"predicate": {"custom_model_data":180}, "model": "custom/pinktea"},
	{"predicate": {"custom_model_data":181}, "model": "custom/yellowtea"},
	{"predicate": {"custom_model_data":182}, "model": "custom/sleepy"},	
	{"predicate": {"custom_model_data":183}, "model": "custom/dwarfrope"},
	{"predicate": {"custom_model_data":184}, "model": "custom/msmktrash"},
	{"predicate": {"custom_model_data":185}, "model": "custom/trolley"},
	{"predicate": {"custom_model_data":186}, "model": "custom/mkbench"},
	{"predicate": {"custom_model_data":187}, "model": "custom/mummy"},
	{"predicate": {"custom_model_data":188}, "model": "custom/thankyoustaff"},
	{"predicate": {"custom_model_data":189}, "model": "custom/happypridemonth"},
	{"predicate": {"custom_model_data":190}, "model": "custom/prideposter"},
	{"predicate": {"custom_model_data":191}, "model": "custom/castmember"},
	{"predicate": {"custom_model_data":192}, "model": "custom/firstvisit"},
	{"predicate": {"custom_model_data":193}, "model": "custom/birthday"},
	{"predicate": {"custom_model_data":194}, "model": "custom/stitchpenny"},
	{"predicate": {"custom_model_data":195}, "model": "custom/matterhorn"},
	{"predicate": {"custom_model_data":196}, "model": "custom/gembarrel"},
	{"predicate": {"custom_model_data":197}, "model": "custom/gembox"},
	{"predicate": {"custom_model_data":198}, "model": "custom/diamondeyes"},
	{"predicate": {"custom_model_data":199}, "model": "custom/pickaxe"},
	{"predicate": {"custom_model_data":200}, "model": "custom/pickaxearm"},
	{"predicate": {"custom_model_data":201}, "model": "custom/chalkboard"},
	{"predicate": {"custom_model_data":202}, "model": "custom/dopey"},
	{"predicate": {"custom_model_data":203}, "model": "custom/gemarm"},
	{"predicate": {"custom_model_data":204}, "model": "custom/fourthears"},
	{"predicate": {"custom_model_data":205}, "model": "custom/gradears"},
	{"predicate": {"custom_model_data":206}, "model": "custom/gradmickey"},
	{"predicate": {"custom_model_data":207}, "model": "custom/micgrad"},
	{"predicate": {"custom_model_data":208}, "model": "custom/bobsled"},
	{"predicate": {"custom_model_data":209}, "model": "custom/barnone"},
	{"predicate": {"custom_model_data":210}, "model": "custom/barntwo"},
	{"predicate": {"custom_model_data":211}, "model": "custom/barnthree"},
	{"predicate": {"custom_model_data":212}, "model": "custom/barnfour"},
	{"predicate": {"custom_model_data":213}, "model": "custom/minerhat"},
	{"predicate": {"custom_model_data":214}, "model": "custom/spacehelmet"},
	{"predicate": {"custom_model_data":215}, "model": "custom/minerhat"},
	{"predicate": {"custom_model_data":216}, "model": "custom/dapperyellow"},
	{"predicate": {"custom_model_data":217}, "model": "custom/dapperpurple"},
	{"predicate": {"custom_model_data":218}, "model": "custom/dapperred"},
	{"predicate": {"custom_model_data":219}, "model": "custom/dapperblue"},
	{"predicate": {"custom_model_data":220}, "model": "custom/linky"},
	{"predicate": {"custom_model_data":221}, "model": "custom/pridesg"},
	{"predicate": {"custom_model_data":222}, "model": "custom/arielbody"},
	{"predicate": {"custom_model_data":223}, "model": "custom/bluelobster"},
	{"predicate": {"custom_model_data":224}, "model": "custom/lobsterred"},
	{"predicate": {"custom_model_data":225}, "model": "custom/clam"},
	{"predicate": {"custom_model_data":226}, "model": "custom/arielboat"},
	{"predicate": {"custom_model_data":227}, "model": "custom/redmicears"},
	{"predicate": {"custom_model_data":228}, "model": "custom/orangemicears"},
	{"predicate": {"custom_model_data":229}, "model": "custom/yellowmicears"},
	{"predicate": {"custom_model_data":230}, "model": "custom/limemicears"},
	{"predicate": {"custom_model_data":231}, "model": "custom/greenmicears"},
	{"predicate": {"custom_model_data":232}, "model": "custom/lbluemicears"},
	{"predicate": {"custom_model_data":233}, "model": "custom/bluemicears"},
	{"predicate": {"custom_model_data":234}, "model": "custom/magmicears"},
	{"predicate": {"custom_model_data":235}, "model": "custom/purplemicears"},
	{"predicate": {"custom_model_data":236}, "model": "custom/cyanmicears"},
	{"predicate": {"custom_model_data":237}, "model": "custom/octopus"},
	{"predicate": {"custom_model_data":238}, "model": "custom/bluestarf"},
	{"predicate": {"custom_model_data":239}, "model": "custom/pinkstarf"},
	{"predicate": {"custom_model_data":240}, "model": "custom/greenstarf"},
	{"predicate": {"custom_model_data":241}, "model": "custom/purplestarf"},
	{"predicate": {"custom_model_data":242}, "model": "custom/orangestarf"},
	{"predicate": {"custom_model_data":243}, "model": "custom/arielturtle"},
	{"predicate": {"custom_model_data":244}, "model": "custom/arielride"},
	{"predicate": {"custom_model_data":245}, "model": "custom/ursluarightarm"},
	{"predicate": {"custom_model_data":246}, "model": "custom/urslualeftarm"},
	{"predicate": {"custom_model_data":247}, "model": "custom/ursulabody"},
	{"predicate": {"custom_model_data":248}, "model": "custom/ursulahead"},
	{"predicate": {"custom_model_data":249}, "model": "custom/leftclaw"},
	{"predicate": {"custom_model_data":250}, "model": "custom/rightclaw"},
	{"predicate": {"custom_model_data":251}, "model": "custom/scuttle"},
	{"predicate": {"custom_model_data":252}, "model": "custom/seb"},
	{"predicate": {"custom_model_data":253}, "model": "custom/arielarm"},
	{"predicate": {"custom_model_data":254}, "model": "custom/arieldress"},
	{"predicate": {"custom_model_data":255}, "model": "custom/kingtrident"},
	{"predicate": {"custom_model_data":256}, "model": "custom/scuttlewings"},
	{"predicate": {"custom_model_data":257}, "model": "custom/wondrous"},
	{"predicate": {"custom_model_data":258}, "model": "custom/prideparade"},
	{"predicate": {"custom_model_data":259}, "model": "custom/fishone"},
	{"predicate": {"custom_model_data":260}, "model": "custom/fishtwo"},
	{"predicate": {"custom_model_data":261}, "model": "custom/sw-carbody"},
	{"predicate": {"custom_model_data":262}, "model": "custom/sw-wheel"},
	{"predicate": {"custom_model_data":263}, "model": "custom/sw-steeringwheel"},
	{"predicate": {"custom_model_data":264}, "model": "custom/phoneclock"},
	{"predicate": {"custom_model_data":265}, "model": "custom/peoplemover"},
	{"predicate": {"custom_model_data":270}, "model": "custom/yellowsung"},
	{"predicate": {"custom_model_data":271}, "model": "custom/redsung"},
	{"predicate": {"custom_model_data":272}, "model": "custom/purplesung"},
	{"predicate": {"custom_model_data":273}, "model": "custom/orangesung"},
	{"predicate": {"custom_model_data":277}, "model": "custom/greensung"},
	{"predicate": {"custom_model_data":278}, "model": "custom/bluesung"},
	{"predicate": {"custom_model_data":279}, "model": "custom/stitchhb"},
	{"predicate": {"custom_model_data":280}, "model": "custom/burgerhb"},
	{"predicate": {"custom_model_data":281}, "model": "custom/circustrash"},
	{"predicate": {"custom_model_data":282}, "model": "custom/mkfantrash"},
	{"predicate": {"custom_model_data":283}, "model": "custom/redsunny"},
	{"predicate": {"custom_model_data":284}, "model": "custom/bluesunny"},
	{"predicate": {"custom_model_data":285}, "model": "custom/greensunny"},
	{"predicate": {"custom_model_data":286}, "model": "custom/yellowsunny"},
	{"predicate": {"custom_model_data":287}, "model": "custom/orangesunny"},
	{"predicate": {"custom_model_data":288}, "model": "custom/purplesunny"},
	{"predicate": {"custom_model_data":289}, "model": "custom/daisyduckhb"},
	{"predicate": {"custom_model_data":290}, "model": "custom/donaldhb"},
	{"predicate": {"custom_model_data":291}, "model": "custom/elementalhb"},
	{"predicate": {"custom_model_data":292}, "model": "custom/encantohb"},
	{"predicate": {"custom_model_data":293}, "model": "custom/happybirthdayhb"},
	{"predicate": {"custom_model_data":294}, "model": "custom/strawberrysquish"},
	{"predicate": {"custom_model_data":295}, "model": "custom/icsquish"},
	{"predicate": {"custom_model_data":296}, "model": "custom/pineapplesquish"},
	{"predicate": {"custom_model_data":297}, "model": "custom/bluesquish"},
	{"predicate": {"custom_model_data":298}, "model": "custom/poohhb"},
	{"predicate": {"custom_model_data":299}, "model": "custom/poohears"},
	{"predicate": {"custom_model_data":300}, "model": "custom/rightbutton"},
	{"predicate": {"custom_model_data":301}, "model": "custom/leftbutton"},
	{"predicate": {"custom_model_data":302}, "model": "custom/rightbuttondisabled"},
	{"predicate": {"custom_model_data":303}, "model": "custom/leftbuttondisabled"},
	{"predicate": {"custom_model_data":304}, "model": "custom/arielmk"},
	{"predicate": {"custom_model_data":305}, "model": "custom/barnstormer"},
	{"predicate": {"custom_model_data":306}, "model": "custom/buzzmk"},
	{"predicate": {"custom_model_data":307}, "model": "custom/carouselmk"},
	{"predicate": {"custom_model_data":308}, "model": "custom/dumbomk"},
	{"predicate": {"custom_model_data":309}, "model": "custom/mkcastle"},
	{"predicate": {"custom_model_data":310}, "model": "custom/orbmk"},
	{"predicate": {"custom_model_data":311}, "model": "custom/philmagic"},
	{"predicate": {"custom_model_data":312}, "model": "custom/ppfmk"},
	{"predicate": {"custom_model_data":313}, "model": "custom/sdmt"},
	{"predicate": {"custom_model_data":314}, "model": "custom/smallworldmk"},
	{"predicate": {"custom_model_data":315}, "model": "custom/spacemk"},
	{"predicate": {"custom_model_data":316}, "model": "custom/teacupmk"},
	{"predicate": {"custom_model_data":317}, "model": "custom/wtpoohmk"},
	{"predicate": {"custom_model_data":318}, "model": "custom/cruiseship"},
	{"predicate": {"custom_model_data":319}, "model": "custom/mkbutton"},
	{"predicate": {"custom_model_data":320}, "model": "custom/creativeb"},
	{"predicate": {"custom_model_data":321}, "model": "custom/belle"},
	{"predicate": {"custom_model_data":322}, "model": "custom/beourguest"},
	{"predicate": {"custom_model_data":323}, "model": "custom/croyaltable"},
	{"predicate": {"custom_model_data":324}, "model": "custom/petesideshow"},
	{"predicate": {"custom_model_data":325}, "model": "custom/phausvillage"},
	{"predicate": {"custom_model_data":326}, "model": "custom/princessfair"},
	{"predicate": {"custom_model_data":327}, "model": "custom/speedway"},
	{"predicate": {"custom_model_data":328}, "model": "custom/halloweenbanner"},
	{"predicate": {"custom_model_data":329}, "model": "custom/miniewitchpur"},
	{"predicate": {"custom_model_data":330}, "model": "custom/miniewitchpnk"},
	{"predicate": {"custom_model_data":331}, "model": "custom/miniewitchgrn"},
	{"predicate": {"custom_model_data":332}, "model": "custom/halloweenbp"},
	{"predicate": {"custom_model_data":333}, "model": "custom/halloweenhb"},
	{"predicate": {"custom_model_data":334}, "model": "custom/halloweenbpg"},
	{"predicate": {"custom_model_data":335}, "model": "custom/halloweenbpp"},
	{"predicate": {"custom_model_data":336}, "model": "custom/halloweenhbp"},
	{"predicate": {"custom_model_data":337}, "model": "custom/halloweenhbg"},
	{"predicate": {"custom_model_data":338}, "model": "custom/halloweenbpm"},
	{"predicate": {"custom_model_data":339}, "model": "custom/halloweenhbm"},
	{"predicate": {"custom_model_data":340}, "model": "custom/itmask"},
	{"predicate": {"custom_model_data":341}, "model": "custom/halloweenmickeywreath"},
	{"predicate": {"custom_model_data":342}, "model": "custom/halloweenears"},
	{"predicate": {"custom_model_data":343}, "model": "custom/halloweenearsp"},
	{"predicate": {"custom_model_data":344}, "model": "custom/halloweenearsm"},
	{"predicate": {"custom_model_data":345}, "model": "custom/clownhammer"},
	{"predicate": {"custom_model_data":346}, "model": "custom/chainsaw"},
	{"predicate": {"custom_model_data":347}, "model": "custom/halloweengarland"},
	{"predicate": {"custom_model_data":348}, "model": "custom/demonhorns"},
	{"predicate": {"custom_model_data":349}, "model": "custom/barrel"},
	{"predicate": {"custom_model_data":350}, "model": "custom/dagger"},
	{"predicate": {"custom_model_data":351}, "model": "custom/witchbrew"},
	{"predicate": {"custom_model_data":352}, "model": "custom/toadcar"},
	{"predicate": {"custom_model_data":353}, "model": "custom/elfhat"},
	{"predicate": {"custom_model_data":354}, "model": "custom/greenhb"},
	{"predicate": {"custom_model_data":355}, "model": "custom/holly"},
	{"predicate": {"custom_model_data":356}, "model": "custom/redhb"},
	{"predicate": {"custom_model_data":357}, "model": "custom/santablue"},
	{"predicate": {"custom_model_data":358}, "model": "custom/santacyan"},
	{"predicate": {"custom_model_data":359}, "model": "custom/santaears"},
	{"predicate": {"custom_model_data":360}, "model": "custom/santahat"},
	{"predicate": {"custom_model_data":361}, "model": "custom/santamagenta"},
	{"predicate": {"custom_model_data":362}, "model": "custom/santapink"},
	{"predicate": {"custom_model_data":363}, "model": "custom/santapurple"},
	{"predicate": {"custom_model_data":364}, "model": "custom/santayellow"},
	{"predicate": {"custom_model_data":365}, "model": "custom/stripbp"},
	{"predicate": {"custom_model_data":366}, "model": "custom/striphb"},
	{"predicate": {"custom_model_data":367}, "model": "custom/christmashbr"},
	{"predicate": {"custom_model_data":368}, "model": "custom/christmashbg"},
	{"predicate": {"custom_model_data":369}, "model": "custom/christmasbpr"},
	{"predicate": {"custom_model_data":370}, "model": "custom/christmasears"},
	{"predicate": {"custom_model_data":371}, "model": "custom/christmasearsbow"},
	{"predicate": {"custom_model_data":372}, "model": "custom/stripears"},
	{"predicate": {"custom_model_data":373}, "model": "custom/kwanzahb"},
	{"predicate": {"custom_model_data":374}, "model": "custom/snowflakehb"},
	{"predicate": {"custom_model_data":375}, "model": "custom/hanukkahhb"},
	{"predicate": {"custom_model_data":376}, "model": "custom/mickeysanta"},
	{"predicate": {"custom_model_data":377}, "model": "custom/christmasbubble"},
	{"predicate": {"custom_model_data":378}, "model": "custom/santasign"},
	{"predicate": {"custom_model_data":379}, "model": "custom/micsanta"},
	{"predicate": {"custom_model_data":380}, "model": "custom/grinch"},
	{"predicate": {"custom_model_data":381}, "model": "custom/gingy"},
	{"predicate": {"custom_model_data":382}, "model": "custom/candycane"},
	{"predicate": {"custom_model_data":383}, "model": "custom/smallclock"},
	{"predicate": {"custom_model_data":384}, "model": "custom/jcricket"},
	{"predicate": {"custom_model_data":385}, "model": "custom/whale"},
	{"predicate": {"custom_model_data":386}, "model": "custom/pincoride"},
	{"predicate": {"custom_model_data":387}, "model": "custom/castlelamp"},
	{"predicate": {"custom_model_data":388}, "model": "custom/iceears"},
	{"predicate": {"custom_model_data":389}, "model": "custom/jcrickethat"}
		
]
}
